pytaskai/__init__.py
pytaskai/adapters/__init__.py
pytaskai/adapters/cli/__init__.py
pytaskai/adapters/cli/cli_app.py
pytaskai/adapters/cli/config.py
pytaskai/adapters/cli/dependency_injection.py
pytaskai/adapters/cli/dto_mappers.py
pytaskai/adapters/cli/commands/__init__.py
pytaskai/adapters/cli/commands/task_commands.py
pytaskai/adapters/cli/formatters/__init__.py
pytaskai/adapters/cli/formatters/output_formatters.py
pytaskai/adapters/mcp/__init__.py
pytaskai/adapters/mcp/__main__.py
pytaskai/adapters/mcp/dependency_injection.py
pytaskai/adapters/mcp/dto_mappers.py
pytaskai/adapters/mcp/error_handlers.py
pytaskai/adapters/mcp/mcp_server.py
pytaskai/adapters/mcp/task_tools.py
pytaskai/application/__init__.py
pytaskai/application/container.py
pytaskai/application/dto/__init__.py
pytaskai/application/dto/task_dto.py
pytaskai/application/interfaces/__init__.py
pytaskai/application/interfaces/ai_service.py
pytaskai/application/interfaces/notification_service.py
pytaskai/application/use_cases/__init__.py
pytaskai/application/use_cases/ai_task_generation.py
pytaskai/application/use_cases/document_management.py
pytaskai/application/use_cases/task_management.py
pytaskai/domain/__init__.py
pytaskai/domain/entities/__init__.py
pytaskai/domain/entities/task.py
pytaskai/domain/repositories/__init__.py
pytaskai/domain/repositories/task_repository.py
pytaskai/domain/services/__init__.py
pytaskai/domain/services/task_service.py
pytaskai/domain/value_objects/__init__.py
pytaskai/domain/value_objects/task_types.py
pytaskai/infrastructure/__init__.py
pytaskai/infrastructure/config/__init__.py
pytaskai/infrastructure/config/ai_config.py
pytaskai/infrastructure/config/database_config.py
pytaskai/infrastructure/external/__init__.py
pytaskai/infrastructure/external/openai_client.py
pytaskai/infrastructure/external/openai_service.py
pytaskai/infrastructure/external/prompt_templates.py
pytaskai/infrastructure/persistence/__init__.py
pytaskai/infrastructure/persistence/database.py
pytaskai-0.3.0.dist-info/LICENSE.md
pytaskai-0.3.0.dist-info/METADATA
pytaskai-0.3.0.dist-info/WHEEL
pytaskai-0.3.0.dist-info/entry_points.txt
pytaskai-0.3.0.dist-info/top_level.txt
pytaskai-0.3.0.dist-info/RECORD
