Metadata-Version: 2.1
Name: pytaskai
Version: 0.3.0
Summary: Minimal AI-powered task management with MCP integration and hexagonal architecture
Author-email: PyTaskAI Contributors <noreply@pytaskai.dev>
License: MIT
Project-URL: Homepage, https://github.com/mak1jk/pytaskai-public
Project-URL: Repository, https://github.com/mak1jk/pytaskai-public
Project-URL: Bug Tracker, https://github.com/mak1jk/pytaskai-public/issues
Project-URL: Changelog, https://github.com/mak1jk/pytaskai-public/blob/main/CHANGELOG.md
Keywords: task-management,ai,mcp,hexagonal-architecture,domain-driven-design,openai,fastmcp
Classifier: Development Status :: 5 - Production/Stable
Classifier: Intended Audience :: Developers
Classifier: License :: OSI Approved :: MIT License
Classifier: Operating System :: OS Independent
Classifier: Programming Language :: Python :: 3
Classifier: Programming Language :: Python :: 3.8
Classifier: Programming Language :: Python :: 3.9
Classifier: Programming Language :: Python :: 3.10
Classifier: Programming Language :: Python :: 3.11
Classifier: Programming Language :: Python :: 3.12
Classifier: Topic :: Software Development :: Libraries :: Python Modules
Classifier: Topic :: Office/Business :: Scheduling
Classifier: Topic :: Scientific/Engineering :: Artificial Intelligence
Requires-Python: >=3.8
License-File: LICENSE.md
Requires-Dist: fastmcp>=0.3.0
Requires-Dist: pydantic>=2.0.0
Requires-Dist: sqlalchemy>=2.0.0
Requires-Dist: openai>=1.0.0
Requires-Dist: click>=8.0.0
Requires-Dist: tabulate>=0.9.0
Requires-Dist: python-dotenv>=1.0.0
Provides-Extra: dev
Requires-Dist: pytest>=7.0.0; extra == "dev"
Requires-Dist: pytest-cov>=4.0.0; extra == "dev"
Requires-Dist: pytest-asyncio>=0.20.0; extra == "dev"
Requires-Dist: black>=23.0.0; extra == "dev"
Requires-Dist: isort>=5.12.0; extra == "dev"
Requires-Dist: mypy>=1.0.0; extra == "dev"
Requires-Dist: flake8>=6.0.0; extra == "dev"
Requires-Dist: types-tabulate>=0.9.0; extra == "dev"
